chatsapi/__init__.py
chatsapi/chatsapi.py
tests/__init__.py
tests/test_chatsapi.py
chatsapi-0.1.0.dist-info/METADATA
chatsapi-0.1.0.dist-info/WHEEL
chatsapi-0.1.0.dist-info/top_level.txt
chatsapi-0.1.0.dist-info/RECORD
