Metadata-Version: 2.1
Name: chatsapi
Version: 0.1.0
Summary: The World's Fastest AI Agent Framework. Based on SBERT & SpaCy Transforms.
Home-page: https://github.com/chatsapi/chatsapi
Author: Sathnindu Kottage
Author-email: hello@bysatha.com
Classifier: Programming Language :: Python :: 3
Classifier: License :: OSI Approved :: MIT License
Classifier: Operating System :: OS Independent
Requires-Python: >=3.7
Requires-Dist: sentence_transformers
Requires-Dist: spacy
Requires-Dist: hnswlib
Requires-Dist: rank_bm25
Requires-Dist: llama-index
Requires-Dist: llama-index-llms-openai
Requires-Dist: llama-index-llms-gemini
Requires-Dist: llama-index-llms-llama-api
Requires-Dist: llama-index-llms-ollama
